AIRadarLib/AIradar_autopara.py
AIRadarLib/__init__.py
AIRadarLib/channel_simulation.py
AIRadarLib/datautil.py
AIRadarLib/modeling_RadarNet.py
AIRadarLib/modeling_TimeNet.py
AIRadarLib/modeling_transformer.py
AIRadarLib/ofdm_decoder.py
AIRadarLib/pretrain_dataset.py
AIRadarLib/radar_det.py
AIRadarLib/signal_processing.py
AIRadarLib/target_utils.py
AIRadarLib/visualization.py
AIRadarLib/waveform_test_adf4159.py
AIRadarLib/waveform_utils.py
airadarlib-0.1.0.dist-info/WHEEL
airadarlib-0.1.0.dist-info/METADATA
airadarlib-0.1.0.dist-info/RECORD
