Metadata-Version: 2.4
Name: AIRadarLib
Version: 0.1.0
Summary: AIRadar python package
Author-email: Kaikai Liu <kaikai.liu@sjsu.edu>
Requires-Python: >=3.8
Requires-Dist: numpy
Project-URL: Homepage, https://github.com/lkk688/AIsensing/tree/main/AIRadar
